posthog_mcp/__init__.py
posthog_mcp/__main__.py
posthog_mcp/server.py
posthog_mcp/core/__init__.py
posthog_mcp/core/client.py
posthog_mcp/core/settings.py
posthog_mcp/tools/__init__.py
posthog_mcp/tools/annotations/annotations.py
posthog_mcp/tools/docs/docs.py
posthog_mcp/tools/insights/insights.py
posthog_mcp/tools/projects/projects.py
mseep_posthog_mcp-0.1.0.dist-info/METADATA
mseep_posthog_mcp-0.1.0.dist-info/WHEEL
mseep_posthog_mcp-0.1.0.dist-info/entry_points.txt
mseep_posthog_mcp-0.1.0.dist-info/licenses/LICENSE
mseep_posthog_mcp-0.1.0.dist-info/RECORD
